cihub/__init__.py
cihub/__main__.py
cihub/aggregation.py
cihub/badges.py
cihub/ci_config.py
cihub/ci_report.py
cihub/ci_runner.py
cihub/cli.py
cihub/correlation.py
cihub/exit_codes.py
cihub/reporting.py
cihub/types.py
cihub/ai/__init__.py
cihub/ai/claude_client.py
cihub/ai/context.py
cihub/ai/enhance.py
cihub/cli_parsers/__init__.py
cihub/cli_parsers/adr.py
cihub/cli_parsers/builder.py
cihub/cli_parsers/commands_cmd.py
cihub/cli_parsers/common.py
cihub/cli_parsers/config.py
cihub/cli_parsers/core.py
cihub/cli_parsers/discover.py
cihub/cli_parsers/dispatch.py
cihub/cli_parsers/docs.py
cihub/cli_parsers/fix.py
cihub/cli_parsers/gradle.py
cihub/cli_parsers/hub.py
cihub/cli_parsers/pom.py
cihub/cli_parsers/profile_cmd.py
cihub/cli_parsers/registry.py
cihub/cli_parsers/registry_cmd.py
cihub/cli_parsers/repo_cmd.py
cihub/cli_parsers/repo_setup.py
cihub/cli_parsers/report.py
cihub/cli_parsers/secrets.py
cihub/cli_parsers/templates.py
cihub/cli_parsers/threshold_cmd.py
cihub/cli_parsers/tool_cmd.py
cihub/cli_parsers/triage.py
cihub/cli_parsers/types.py
cihub/cli_parsers/hub_ci/__init__.py
cihub/cli_parsers/hub_ci/badges.py
cihub/cli_parsers/hub_ci/java_tools.py
cihub/cli_parsers/hub_ci/python_tools.py
cihub/cli_parsers/hub_ci/release.py
cihub/cli_parsers/hub_ci/security.py
cihub/cli_parsers/hub_ci/smoke.py
cihub/cli_parsers/hub_ci/test_metrics.py
cihub/cli_parsers/hub_ci/thresholds.py
cihub/cli_parsers/hub_ci/validation.py
cihub/commands/__init__.py
cihub/commands/adr.py
cihub/commands/ai_loop.py
cihub/commands/ai_loop_analysis.py
cihub/commands/ai_loop_artifacts.py
cihub/commands/ai_loop_ci.py
cihub/commands/ai_loop_contracts.py
cihub/commands/ai_loop_guardrails.py
cihub/commands/ai_loop_local.py
cihub/commands/ai_loop_remote.py
cihub/commands/ai_loop_results.py
cihub/commands/ai_loop_review.py
cihub/commands/ai_loop_session.py
cihub/commands/ai_loop_settings.py
cihub/commands/ai_loop_types.py
cihub/commands/check.py
cihub/commands/ci.py
cihub/commands/commands_cmd.py
cihub-1.0.16.dist-info/licenses/LICENSE
cihub-1.0.16.dist-info/METADATA
cihub-1.0.16.dist-info/WHEEL
cihub-1.0.16.dist-info/entry_points.txt
cihub-1.0.16.dist-info/top_level.txt
cihub-1.0.16.dist-info/RECORD
