Metadata-Version: 2.4
Name: cihub
Version: 1.0.16
Summary: Centralized CI/CD orchestration hub for multi-repository pipelines
Author: jguida941
License: Elastic License 2.0
Project-URL: Homepage, https://github.com/jguida941/ci-cd-hub
Project-URL: Repository, https://github.com/jguida941/ci-cd-hub
Project-URL: Documentation, https://github.com/jguida941/ci-cd-hub/tree/main/docs
Project-URL: Issues, https://github.com/jguida941/ci-cd-hub/issues
Keywords: ci,cd,github-actions,devops,automation,testing,linting,security
Classifier: Development Status :: 4 - Beta
Classifier: Environment :: Console
Classifier: Intended Audience :: Developers
Classifier: Operating System :: OS Independent
Classifier: Programming Language :: Python :: 3
Classifier: Programming Language :: Python :: 3.10
Classifier: Programming Language :: Python :: 3.11
Classifier: Programming Language :: Python :: 3.12
Classifier: Topic :: Software Development :: Quality Assurance
Classifier: Topic :: Software Development :: Testing
Classifier: Topic :: Software Development :: Build Tools
Requires-Python: >=3.10
License-File: LICENSE
Requires-Dist: pyyaml>=6.0
Requires-Dist: jsonschema>=4.21.0
Requires-Dist: defusedxml>=0.7.1
Provides-Extra: dev
Requires-Dist: pytest>=7.0; extra == "dev"
Requires-Dist: pytest-cov>=4.0; extra == "dev"
Requires-Dist: pytest-benchmark>=5.0.0; extra == "dev"
Requires-Dist: pytest-xdist>=3.0; extra == "dev"
Requires-Dist: hypothesis>=6.0; extra == "dev"
Requires-Dist: syrupy>=5.0.0; extra == "dev"
Requires-Dist: mutmut>=2.4.0; extra == "dev"
Requires-Dist: ruff>=0.8.0; extra == "dev"
Requires-Dist: black>=24.0; extra == "dev"
Requires-Dist: isort>=5.12.0; extra == "dev"
Requires-Dist: yamllint>=1.33.0; extra == "dev"
Requires-Dist: zizmor>=1.0.0; extra == "dev"
Requires-Dist: mypy>=1.8.0; extra == "dev"
Requires-Dist: types-PyYAML>=6.0; extra == "dev"
Requires-Dist: types-jsonschema>=4.0; extra == "dev"
Requires-Dist: bandit[toml]>=1.7.9; extra == "dev"
Requires-Dist: pip-audit>=2.7.0; extra == "dev"
Requires-Dist: pre-commit>=3.6.0; extra == "dev"
Requires-Dist: pip-licenses>=4.3.0; extra == "dev"
Requires-Dist: questionary>=2.0.0; extra == "dev"
Requires-Dist: rich>=13.0.0; extra == "dev"
Provides-Extra: ci
Requires-Dist: pytest>=7.0; extra == "ci"
Requires-Dist: pytest-cov>=4.0; extra == "ci"
Requires-Dist: pytest-benchmark>=5.0.0; extra == "ci"
Requires-Dist: syrupy>=4.0.0; extra == "ci"
Requires-Dist: hypothesis>=6.0; extra == "ci"
Requires-Dist: mutmut>=2.4.0; extra == "ci"
Requires-Dist: ruff>=0.8.0; extra == "ci"
Requires-Dist: mypy>=1.8.0; extra == "ci"
Requires-Dist: yamllint>=1.33.0; extra == "ci"
Requires-Dist: types-PyYAML>=6.0; extra == "ci"
Requires-Dist: black>=24.0; extra == "ci"
Requires-Dist: isort>=5.12.0; extra == "ci"
Requires-Dist: bandit[toml]>=1.7.9; extra == "ci"
Requires-Dist: pip-audit>=2.7.0; extra == "ci"
Requires-Dist: semgrep>=1.90.0; extra == "ci"
Requires-Dist: zizmor>=1.0.0; extra == "ci"
Requires-Dist: pip-licenses>=4.3.0; extra == "ci"
Provides-Extra: wizard
Requires-Dist: questionary>=2.0.0; extra == "wizard"
Requires-Dist: rich>=13.0.0; extra == "wizard"
Dynamic: license-file
